flask_threaded_sockets/__init__.py
flask_threaded_sockets/exceptions.py
flask_threaded_sockets/flask.py
flask_threaded_sockets/header.py
flask_threaded_sockets/logging.py
flask_threaded_sockets/serving.py
flask_threaded_sockets/utf8validator.py
flask_threaded_sockets/websocket.py
flask_threaded_sockets-0.3.2.dist-info/LICENSE
flask_threaded_sockets-0.3.2.dist-info/WHEEL
flask_threaded_sockets-0.3.2.dist-info/METADATA
flask_threaded_sockets-0.3.2.dist-info/RECORD
